fcutils/__init__.py
fcutils/_file.py
fcutils/_video.py
fcutils/path.py
fcutils/progress.py
fcutils/time.py
fcutils/video.py
fcutils/maths/__init__.py
fcutils/maths/array.py
fcutils/maths/coordinates.py
fcutils/maths/distributions.py
fcutils/maths/fit.py
fcutils/maths/functions.py
fcutils/maths/geometry.py
fcutils/maths/signals.py
fcutils/plot/__init__.py
fcutils/plot/ax.py
fcutils/plot/distributions.py
fcutils/plot/elements.py
fcutils/plot/figure.py
tests/__init__.py
tests/test_coordinates.py
tests/test_math_array.py
tests/test_path.py
tests/test_track.py
fcutils-1.1.2.8.dist-info/LICENSE
fcutils-1.1.2.8.dist-info/METADATA
fcutils-1.1.2.8.dist-info/WHEEL
fcutils-1.1.2.8.dist-info/top_level.txt
fcutils-1.1.2.8.dist-info/RECORD
